sdrfcheck/__init__.py
sdrfcheck/sdrfchecker.py
sdrfcheck/sdrf/__init__.py
sdrfcheck/sdrf/exceptions.py
sdrfcheck/sdrf/sdrf.py
sdrfcheck/sdrf/sdrf_schema.py
sdrfcheck/tests/__init__.py
sdrfcheck/tests/sdrfchecker_tests.py
sdrfcheck/zooma/__init__.py
sdrfcheck/zooma/zooma.py
sdrfcheck-0.0.4.data/scripts/sdrfchecker.py
sdrfcheck-0.0.4.dist-info/LICENSE
sdrfcheck-0.0.4.dist-info/METADATA
sdrfcheck-0.0.4.dist-info/WHEEL
sdrfcheck-0.0.4.dist-info/top_level.txt
sdrfcheck-0.0.4.dist-info/RECORD
