Metadata-Version: 2.1
Name: sdrfcheck
Version: 0.0.4
Summary: Python tools for SDRF proteomics validation
Home-page: http://github.com/bigbio/sdrfcheck
Author: BigBio Team
Author-email: ypriverol@gmail.com
License: LICENSE
Platform: UNKNOWN
Requires-Python: >=3.4
Requires-Dist: requests
Requires-Dist: pandas-schema
Requires-Dist: pandas
Requires-Dist: ebi-ols-client
Requires-Dist: click
